odoo/addons/apps_product_creator/README.rst
odoo/addons/apps_product_creator/__init__.py
odoo/addons/apps_product_creator/__manifest__.py
odoo/addons/apps_product_creator/data/ir_cron.xml
odoo/addons/apps_product_creator/data/product_attribute.xml
odoo/addons/apps_product_creator/data/product_public_categ_data.xml
odoo/addons/apps_product_creator/i18n/apps_product_creator.pot
odoo/addons/apps_product_creator/i18n/es.po
odoo/addons/apps_product_creator/i18n/es_AR.po
odoo/addons/apps_product_creator/i18n/fr.po
odoo/addons/apps_product_creator/i18n/it.po
odoo/addons/apps_product_creator/models/__init__.py
odoo/addons/apps_product_creator/models/odoo_module.py
odoo/addons/apps_product_creator/models/odoo_module_version.py
odoo/addons/apps_product_creator/models/product_product.py
odoo/addons/apps_product_creator/models/product_template.py
odoo/addons/apps_product_creator/readme/CONFIGURE.rst
odoo/addons/apps_product_creator/readme/CONTRIBUTORS.rst
odoo/addons/apps_product_creator/readme/CREDITS.rst
odoo/addons/apps_product_creator/readme/DESCRIPTION.rst
odoo/addons/apps_product_creator/readme/HISTORY.rst
odoo/addons/apps_product_creator/readme/USAGE.rst
odoo/addons/apps_product_creator/static/description/icon.png
odoo/addons/apps_product_creator/static/description/index.html
odoo/addons/apps_product_creator/tests/__init__.py
odoo/addons/apps_product_creator/tests/test_apps_product_creator.py
odoo/addons/apps_product_creator/views/view_odoo_module.xml
odoo/addons/apps_product_creator/views/view_product_product.xml
odoo13_addon_apps_product_creator-13.0.1.0.1.dev15.dist-info/METADATA
odoo13_addon_apps_product_creator-13.0.1.0.1.dev15.dist-info/WHEEL
odoo13_addon_apps_product_creator-13.0.1.0.1.dev15.dist-info/top_level.txt
odoo13_addon_apps_product_creator-13.0.1.0.1.dev15.dist-info/RECORD
