Metadata-Version: 2.1
Name: odoo13-addon-apps_product_creator
Version: 13.0.1.0.1.dev15
Summary: Create a product variant (by version) for every module found in the Github repositories
Home-page: https://github.com/OCA/apps-store
Author: Odoo Community Association (OCA), BizzAppDev
Author-email: support@odoo-community.org
License: AGPL-3
Classifier: Programming Language :: Python
Classifier: Framework :: Odoo
Classifier: Framework :: Odoo :: 13.0
Classifier: License :: OSI Approved :: GNU Affero General Public License v3
Requires-Python: >=3.5
Requires-Dist: odoo13-addon-github-connector-oca
Requires-Dist: odoo13-addon-github-connector-odoo
Requires-Dist: odoo<13.1dev,>=13.0a
